kalasiris/Histogram.py
kalasiris/PathSet.py
kalasiris/__init__.py
kalasiris/cube.py
kalasiris/cubenormfile.py
kalasiris/fromlist.py
kalasiris/k_funcs.py
kalasiris/kalasiris.py
kalasiris/pysis.py
kalasiris/specialpixels.py
kalasiris/sweetened.py
kalasiris/version.py
kalasiris-1.11.0.dist-info/AUTHORS.rst
kalasiris-1.11.0.dist-info/LICENSE
kalasiris-1.11.0.dist-info/METADATA
kalasiris-1.11.0.dist-info/WHEEL
kalasiris-1.11.0.dist-info/top_level.txt
kalasiris-1.11.0.dist-info/RECORD
