Metadata-Version: 2.1
Name: kalasiris
Version: 1.11.0
Summary: A Python library to wrap functions and functionality for the Integrated Software for Imagers and Spectrometers (ISIS).
Maintainer-email: Ross Beyer <rbeyer@seti.org>
Project-URL: Repository, https://github.com/rbeyer/kalasiris
Classifier: Development Status :: 5 - Production/Stable
Classifier: Intended Audience :: Developers
Classifier: Intended Audience :: Science/Research
Classifier: License :: OSI Approved :: BSD License
Classifier: Natural Language :: English
Classifier: Programming Language :: Python :: 3.8
Classifier: Programming Language :: Python :: 3.9
Requires-Python: >=3.8
License-File: LICENSE
License-File: AUTHORS.rst
